spakky/domain/__init__.py
spakky/domain/application/__init__.py
spakky/domain/application/command.py
spakky/domain/application/query.py
spakky/domain/error.py
spakky/domain/models/__init__.py
spakky/domain/models/aggregate_root.py
spakky/domain/models/entity.py
spakky/domain/models/event.py
spakky/domain/models/value_object.py
spakky_domain-5.0.1.dist-info/WHEEL
spakky_domain-5.0.1.dist-info/METADATA
spakky_domain-5.0.1.dist-info/RECORD
