Metadata-Version: 2.3
Name: spakky-domain
Version: 5.0.1
Summary: DDD building blocks for Spakky Framework (Entity, AggregateRoot, ValueObject, DomainEvent, CQRS)
Author: Spakky
Author-email: Spakky <sejong418@icloud.com>
Requires-Dist: spakky>=5.0.1
Requires-Python: >=3.11
